setup.py
django_orienteer.egg-info/PKG-INFO
django_orienteer.egg-info/SOURCES.txt
django_orienteer.egg-info/dependency_links.txt
django_orienteer.egg-info/top_level.txt
orienteer/__init__.py
orienteer/templatetags/__init__.py
orienteer/templatetags/orienteer.py