Metadata-Version: 1.0
Name: django-orienteer
Version: 0.1
Summary: Django Compass App
Home-page: http://github.com/sentineldesign/django-orienteer/
Author: Drew Yeaton
Author-email: drew@sentineldesign.net
License: Apache License, Version 2.0
Keywords: django sass compass css
Platform: Platform Independent
Classifier: Development Status :: 4 - Beta
Classifier: Intended Audience :: Developers
Classifier: License :: OSI Approved :: GNU General Public License (GPL)
Classifier: Natural Language :: English
Classifier: Operating System :: OS Independent
Classifier: Programming Language :: Python
Classifier: Topic :: Software Development :: Libraries :: Python Modules
